pyfloc/__init__.py
pyfloc/cluster.py
pyfloc-0.0.3.dist-info/METADATA
pyfloc-0.0.3.dist-info/RECORD
pyfloc-0.0.3.dist-info/WHEEL
pyfloc-0.0.3.dist-info/top_level.txt
